{
"meta":{"test_sets":[],"test_metrics":[],"learn_metrics":[{"best_value":"Min","name":"RMSE"}],"launch_mode":"Train","parameters":"","iteration_count":25,"learn_sets":["learn"],"name":"experiment"},
"iterations":[
{"learn":[0.1603985306],"iteration":0,"passed_time":0.1881313011,"remaining_time":4.515151227},
{"learn":[0.08457213305],"iteration":1,"passed_time":0.4280192542,"remaining_time":4.922221423},
{"learn":[0.04593885808],"iteration":2,"passed_time":0.5509424173,"remaining_time":4.040244393},
{"learn":[0.02486098499],"iteration":3,"passed_time":1.133437069,"remaining_time":5.950544614},
{"learn":[0.01524638417],"iteration":4,"passed_time":1.451619181,"remaining_time":5.806476723},
{"learn":[0.007874689934],"iteration":5,"passed_time":2.010726225,"remaining_time":6.367299712},
{"learn":[0.004050346917],"iteration":6,"passed_time":2.58385635,"remaining_time":6.644202043},
{"learn":[0.002362726718],"iteration":7,"passed_time":3.166257084,"remaining_time":6.728296303},
{"learn":[0.001510392671],"iteration":8,"passed_time":3.198539,"remaining_time":5.686291556},
{"learn":[0.001076227339],"iteration":9,"passed_time":4.515387023,"remaining_time":6.773080535},
{"learn":[0.0009066681457],"iteration":10,"passed_time":5.6318512,"remaining_time":7.167810619},
{"learn":[0.0008526104848],"iteration":11,"passed_time":6.741353734,"remaining_time":7.303133212},
{"learn":[0.00083936344],"iteration":12,"passed_time":6.951888706,"remaining_time":6.417128036},
{"learn":[0.0008353671787],"iteration":13,"passed_time":7.447411395,"remaining_time":5.851537525},
{"learn":[0.0008345455892],"iteration":14,"passed_time":7.968397111,"remaining_time":5.312264741},
{"learn":[0.0008342158449],"iteration":15,"passed_time":8.091791784,"remaining_time":4.551632878},
{"learn":[0.000834106472],"iteration":16,"passed_time":9.246786048,"remaining_time":4.351428729},
{"learn":[0.0008340774595],"iteration":17,"passed_time":10.35763261,"remaining_time":4.027968237},
{"learn":[0.0008340669161],"iteration":18,"passed_time":10.80566961,"remaining_time":3.412316719},
{"learn":[0.0008340641279],"iteration":19,"passed_time":12.02203852,"remaining_time":3.005509629},
{"learn":[0.0008340633708],"iteration":20,"passed_time":12.21705754,"remaining_time":2.32705858},
{"learn":[0.0008340631612],"iteration":21,"passed_time":12.53873735,"remaining_time":1.709827821},
{"learn":[0.0008340630965],"iteration":22,"passed_time":13.03861963,"remaining_time":1.133793011},
{"learn":[0.0008340630812],"iteration":23,"passed_time":14.28226868,"remaining_time":0.5950945285},
{"learn":[0.0008340630754],"iteration":24,"passed_time":15.39196672,"remaining_time":0}
]}